ssb_kostra_python/__init__.py
ssb_kostra_python/kommunekorr.py
ssb_kostra_python/py.typed
ssb_kostra_python-0.0.3.dist-info/LICENSE
ssb_kostra_python-0.0.3.dist-info/METADATA
ssb_kostra_python-0.0.3.dist-info/WHEEL
ssb_kostra_python-0.0.3.dist-info/RECORD
