Metadata-Version: 2.3
Name: ssb-kostra-python
Version: 0.0.3
Summary: SSB Kostra Python
License: MIT
Author: Magne Furuholmen Myhren
Author-email: mfm@ssb.no
Requires-Python: >=3.10,<4.0
Classifier: Development Status :: 4 - Beta
Classifier: License :: OSI Approved :: MIT License
Classifier: Programming Language :: Python :: 3
Classifier: Programming Language :: Python :: 3.10
Classifier: Programming Language :: Python :: 3.11
Classifier: Programming Language :: Python :: 3.12
Classifier: Programming Language :: Python :: 3.13
Requires-Dist: pandas (>=2.2.3)
Requires-Dist: pandas-stubs (>=2.2.3.241126)
Requires-Dist: ssb-klass-python (>=1.0.0)
Project-URL: Changelog, https://github.com/statisticsnorway/ssb-kostra-python/releases
Project-URL: Documentation, https://statisticsnorway.github.io/ssb-kostra-python
Project-URL: Homepage, https://github.com/statisticsnorway/ssb-kostra-python
Project-URL: Repository, https://github.com/statisticsnorway/ssb-kostra-python
